[
  {
    "f1": 2,
    "f2": 91.3,
    "f3": 10,
    "f12": "603200",
    "f13": 1,
    "f14": "上海洗霸",
    "f62": 155805632,
    "f66": 192630336,
    "f69": 13.8,
    "f72": -36824704,
    "f75": -2.64,
    "f78": -76098704,
    "f81": -5.45,
    "f84": -79706922,
    "f87": -5.71,
    "f124": 1757059895,
    "f184": 11.16,
    "f204": "-",
    "f205": "-",
    "f206": "-"
  },
  {
    "f1": 2,
    "f2": 9.86,
    "f3": 7.17,
    "f12": "002887",
    "f13": 0,
    "f14": "绿茵生态",
    "f62": 24817731,
    "f66": 4746981,
    "f69": 1.47,
    "f72": 20070750,
    "f75": 6.23,
    "f78": -1551651,
    "f81": -0.48,
    "f84": -23266081,
    "f87": -7.22,
    "f124": 1757057679,
    "f184": 7.7,
    "f204": "-",
    "f205": "-",
    "f206": "-"
  },
  {
    "f1": 2,
    "f2": 14.68,
    "f3": 3.31,
    "f12": "002973",
    "f13": 0,
    "f14": "侨银股份",
    "f62": 21923273,
    "f66": 2745156,
    "f69": 1.56,
    "f72": 19178117,
    "f75": 10.92,
    "f78": -6934136,
    "f81": -3.95,
    "f84": -14989137,
    "f87": -8.53,
    "f124": 1757057667,
    "f184": 12.48,
    "f204": "-",
    "f205": "-",
    "f206": "-"
  },
  {
    "f1": 2,
    "f2": 4.13,
    "f3": 2.74,
    "f12": "002266",
    "f13": 0,
    "f14": "浙富控股",
    "f62": 18213946,
    "f66": 18448512,
    "f69": 1.57,
    "f72": -234566,
    "f75": -0.02,
    "f78": 73536384,
    "f81": 6.27,
    "f84": -91750320,
    "f87": -7.82,
    "f124": 1757057685,
    "f184": 1.55,
    "f204": "-",
    "f205": "-",
    "f206": "-"
  },
  {
    "f1": 2,
    "f2": 11.38,
    "f3": -3.15,
    "f12": "603177",
    "f13": 1,
    "f14": "德创环保",
    "f62": 15959273,
    "f66": 4588606,
    "f69": 1.55,
    "f72": 11370667,
    "f75": 3.85,
    "f78": -10318258,
    "f81": -3.49,
    "f84": -5641016,
    "f87": -1.91,
    "f124": 1757059893,
    "f184": 5.4,
    "f204": "-",
    "f205": "-",
    "f206": "-"
  },
  {
    "f1": 2,
    "f2": 32.35,
    "f3": 5.48,
    "f12": "300631",
    "f13": 0,
    "f14": "久吾高科",
    "f62": 15903652,
    "f66": 12137954,
    "f69": 4.78,
    "f72": 3765698,
    "f75": 1.48,
    "f78": 1096749,
    "f81": 0.43,
    "f84": -17000400,
    "f87": -6.69,
    "f124": 1757057697,
    "f184": 6.26,
    "f204": "-",
    "f205": "-",
    "f206": "-"
  },
  {
    "f1": 2,
    "f2": 8.04,
    "f3": 0.63,
    "f12": "300388",
    "f13": 0,
    "f14": "节能国祯",
    "f62": 14976009,
    "f66": -52639,
    "f69": -0.03,
    "f72": 15028648,
    "f75": 8.81,
    "f78": -11180249,
    "f81": -6.55,
    "f84": -3795760,
    "f87": -2.22,
    "f124": 1757057670,
    "f184": 8.78,
    "f204": "-",
    "f205": "-",
    "f206": "-"
  },
  {
    "f1": 2,
    "f2": 12.65,
    "f3": 2.35,
    "f12": "000920",
    "f13": 0,
    "f14": "沃顿科技",
    "f62": 13822218,
    "f66": 443909,
    "f69": 0.24,
    "f72": 13378309,
    "f75": 7.24,
    "f78": 412896,
    "f81": 0.22,
    "f84": -14235114,
    "f87": -7.71,
    "f124": 1757057658,
    "f184": 7.48,
    "f204": "-",
    "f205": "-",
    "f206": "-"
  },
  {
    "f1": 2,
    "f2": 5.16,
    "f3": 0.39,
    "f12": "300425",
    "f13": 0,
    "f14": "中建环能",
    "f62": 13701016,
    "f66": -2774859,
    "f69": -3.42,
    "f72": 16475875,
    "f75": 20.3,
    "f78": -6796141,
    "f81": -8.38,
    "f84": -6904874,
    "f87": -8.51,
    "f124": 1757057700,
    "f184": 16.88,
    "f204": "-",
    "f205": "-",
    "f206": "-"
  },
  {
    "f1": 2,
    "f2": 7.51,
    "f3": 3.87,
    "f12": "300692",
    "f13": 0,
    "f14": "中环环保",
    "f62": 13205598,
    "f66": 3211081,
    "f69": 1.67,
    "f72": 9994517,
    "f75": 5.21,
    "f78": 3820648,
    "f81": 1.99,
    "f84": -17026245,
    "f87": -8.88,
    "f124": 1757057682,
    "f184": 6.89,
    "f204": "-",
    "f205": "-",
    "f206": "-"
  },
  {
    "f1": 2,
    "f2": 5.94,
    "f3": 2.59,
    "f12": "300335",
    "f13": 0,
    "f14": "迪森股份",
    "f62": 12173974,
    "f66": 2751988,
    "f69": 3.25,
    "f72": 9421986,
    "f75": 11.13,
    "f78": -6115865,
    "f81": -7.23,
    "f84": -6058109,
    "f87": -7.16,
    "f124": 1757057697,
    "f184": 14.38,
    "f204": "-",
    "f205": "-",
    "f206": "-"
  },
  {
    "f1": 2,
    "f2": 6.33,
    "f3": 3.09,
    "f12": "300140",
    "f13": 0,
    "f14": "节能环境",
    "f62": 11312220,
    "f66": -1154512,
    "f69": -0.86,
    "f72": 12466732,
    "f75": 9.32,
    "f78": -5376030,
    "f81": -4.02,
    "f84": -5936191,
    "f87": -4.44,
    "f124": 1757057688,
    "f184": 8.45,
    "f204": "-",
    "f205": "-",
    "f206": "-"
  },
  {
    "f1": 2,
    "f2": 6.03,
    "f3": 0.5,
    "f12": "600874",
    "f13": 1,
    "f14": "创业环保",
    "f62": 10601175,
    "f66": 4059296,
    "f69": 4.23,
    "f72": 6541879,
    "f75": 6.81,
    "f78": -593681,
    "f81": -0.62,
    "f84": -10007494,
    "f87": -10.42,
    "f124": 1757059921,
    "f184": 11.04,
    "f204": "-",
    "f205": "-",
    "f206": "-"
  },
  {
    "f1": 2,
    "f2": 5.13,
    "f3": 2.81,
    "f12": "000546",
    "f13": 0,
    "f14": "金圆股份",
    "f62": 9997005,
    "f66": 4568952,
    "f69": 4.32,
    "f72": 5428053,
    "f75": 5.13,
    "f78": -3465297,
    "f81": -3.28,
    "f84": -6531708,
    "f87": -6.18,
    "f124": 1757057646,
    "f184": 9.45,
    "f204": "-",
    "f205": "-",
    "f206": "-"
  },
  {
    "f1": 2,
    "f2": 20.76,
    "f3": 7.68,
    "f12": "832802",
    "f13": 0,
    "f14": "保丽洁",
    "f62": 9949031,
    "f66": 7107841,
    "f69": 4.8,
    "f72": 2841190,
    "f75": 1.92,
    "f78": -2964596,
    "f81": -2,
    "f84": 451787,
    "f87": 0.31,
    "f124": 1757057712,
    "f184": 6.72,
    "f204": "-",
    "f205": "-",
    "f206": "-"
  },
  {
    "f1": 2,
    "f2": 13.76,
    "f3": 1.4,
    "f12": "301127",
    "f13": 0,
    "f14": "武汉天源",
    "f62": 9567420,
    "f66": -800679,
    "f69": -0.73,
    "f72": 10368099,
    "f75": 9.41,
    "f78": -6819587,
    "f81": -6.19,
    "f84": -2747832,
    "f87": -2.49,
    "f124": 1757057667,
    "f184": 8.68,
    "f204": "-",
    "f205": "-",
    "f206": "-"
  },
  {
    "f1": 2,
    "f2": 14.41,
    "f3": 3.97,
    "f12": "300056",
    "f13": 0,
    "f14": "中创环保",
    "f62": 8965214,
    "f66": 9896838,
    "f69": 6.34,
    "f72": -931624,
    "f75": -0.6,
    "f78": 3520380,
    "f81": 2.26,
    "f84": -12485593,
    "f87": -8,
    "f124": 1757057703,
    "f184": 5.75,
    "f204": "-",
    "f205": "-",
    "f206": "-"
  },
  {
    "f1": 2,
    "f2": 6.89,
    "f3": 1.77,
    "f12": "000967",
    "f13": 0,
    "f14": "盈峰环境",
    "f62": 7963603,
    "f66": -12219446,
    "f69": -6.87,
    "f72": 20183049,
    "f75": 11.35,
    "f78": -5428764,
    "f81": -3.05,
    "f84": -2534839,
    "f87": -1.43,
    "f124": 1757057694,
    "f184": 4.48,
    "f204": "-",
    "f205": "-",
    "f206": "-"
  },
  {
    "f1": 2,
    "f2": 19.12,
    "f3": 2.3,
    "f12": "300203",
    "f13": 0,
    "f14": "聚光科技",
    "f62": 7773895,
    "f66": -7874120,
    "f69": -4.09,
    "f72": 15648015,
    "f75": 8.14,
    "f78": -2346839,
    "f81": -1.22,
    "f84": -5427056,
    "f87": -2.82,
    "f124": 1757057658,
    "f184": 4.04,
    "f204": "-",
    "f205": "-",
    "f206": "-"
  },
  {
    "f1": 2,
    "f2": 5.09,
    "f3": 2.21,
    "f12": "831370",
    "f13": 0,
    "f14": "新安洁",
    "f62": 7495006,
    "f66": 2231003,
    "f69": 3.36,
    "f72": 5264003,
    "f75": 7.93,
    "f78": 3584064,
    "f81": 5.4,
    "f84": 1457630,
    "f87": 2.2,
    "f124": 1757057712,
    "f184": 11.3,
    "f204": "-",
    "f205": "-",
    "f206": "-"
  },
  {
    "f1": 2,
    "f2": 12.71,
    "f3": 2.83,
    "f12": "600292",
    "f13": 1,
    "f14": "远达环保",
    "f62": 7393846,
    "f66": 3620618,
    "f69": 1.64,
    "f72": 3773228,
    "f75": 1.7,
    "f78": -11576078,
    "f81": -5.23,
    "f84": 4182232,
    "f87": 1.89,
    "f124": 1757059904,
    "f184": 3.34,
    "f204": "-",
    "f205": "-",
    "f206": "-"
  },
  {
    "f1": 2,
    "f2": 26.6,
    "f3": 1.29,
    "f12": "600323",
    "f13": 1,
    "f14": "瀚蓝环境",
    "f62": 6233244,
    "f66": 9637904,
    "f69": 5.17,
    "f72": -3404660,
    "f75": -1.83,
    "f78": -4355733,
    "f81": -2.34,
    "f84": -1877512,
    "f87": -1.01,
    "f124": 1757059918,
    "f184": 3.34,
    "f204": "-",
    "f205": "-",
    "f206": "-"
  },
  {
    "f1": 2,
    "f2": 15.16,
    "f3": 2.43,
    "f12": "002645",
    "f13": 0,
    "f14": "华宏科技",
    "f62": 6210593,
    "f66": -4670612,
    "f69": -1.41,
    "f72": 10881205,
    "f75": 3.28,
    "f78": 10578999,
    "f81": 3.19,
    "f84": -16789592,
    "f87": -5.06,
    "f124": 1757057667,
    "f184": 1.87,
    "f204": "-",
    "f205": "-",
    "f206": "-"
  },
  {
    "f1": 2,
    "f2": 4.3,
    "f3": 0.47,
    "f12": "300190",
    "f13": 0,
    "f14": "维尔利",
    "f62": 6073665,
    "f66": -3257271,
    "f69": -3.13,
    "f72": 9330936,
    "f75": 8.97,
    "f78": 7588343,
    "f81": 7.29,
    "f84": -13662007,
    "f87": -13.13,
    "f124": 1757057661,
    "f184": 5.84,
    "f204": "-",
    "f205": "-",
    "f206": "-"
  },
  {
    "f1": 2,
    "f2": 8.17,
    "f3": 0.12,
    "f12": "601200",
    "f13": 1,
    "f14": "上海环境",
    "f62": 5841256,
    "f66": 607234,
    "f69": 0.69,
    "f72": 5234022,
    "f75": 5.92,
    "f78": 588719,
    "f81": 0.67,
    "f84": -6429975,
    "f87": -7.27,
    "f124": 1757059915,
    "f184": 6.61,
    "f204": "-",
    "f205": "-",
    "f206": "-"
  },
  {
    "f1": 2,
    "f2": 6.79,
    "f3": 1.8,
    "f12": "603126",
    "f13": 1,
    "f14": "中材节能",
    "f62": 5524657,
    "f66": 2846525,
    "f69": 3.89,
    "f72": 2678132,
    "f75": 3.66,
    "f78": -115631,
    "f81": -0.16,
    "f84": -5409026,
    "f87": -7.39,
    "f124": 1757059902,
    "f184": 7.55,
    "f204": "-",
    "f205": "-",
    "f206": "-"
  },
  {
    "f1": 2,
    "f2": 12.65,
    "f3": 6.3,
    "f12": "603903",
    "f13": 1,
    "f14": "中持股份",
    "f62": 5417670,
    "f66": 13794339,
    "f69": 4.56,
    "f72": -8376669,
    "f75": -2.77,
    "f78": 18071692,
    "f81": 5.98,
    "f84": -23489362,
    "f87": -7.77,
    "f124": 1757059922,
    "f184": 1.79,
    "f204": "-",
    "f205": "-",
    "f206": "-"
  },
  {
    "f1": 2,
    "f2": 198.18,
    "f3": 3.75,
    "f12": "300779",
    "f13": 0,
    "f14": "惠城环保",
    "f62": 5025693,
    "f66": 19218544,
    "f69": 2.73,
    "f72": -14192851,
    "f75": -2.01,
    "f78": 1134912,
    "f81": 0.16,
    "f84": -6160605,
    "f87": -0.87,
    "f124": 1757057667,
    "f184": 0.71,
    "f204": "-",
    "f205": "-",
    "f206": "-"
  },
  {
    "f1": 2,
    "f2": 10.84,
    "f3": 3.53,
    "f12": "605069",
    "f13": 1,
    "f14": "正和生态",
    "f62": 5010138,
    "f66": 7722780,
    "f69": 14.43,
    "f72": -2712642,
    "f75": -5.07,
    "f78": -2358172,
    "f81": -4.4,
    "f84": -2651966,
    "f87": -4.95,
    "f124": 1757059903,
    "f184": 9.36,
    "f204": "-",
    "f205": "-",
    "f206": "-"
  },
  {
    "f1": 2,
    "f2": 15.03,
    "f3": 5.85,
    "f12": "300614",
    "f13": 0,
    "f14": "百川畅银",
    "f62": 4692960,
    "f66": -743985,
    "f69": -1.42,
    "f72": 5436945,
    "f75": 10.37,
    "f78": -1626269,
    "f81": -3.1,
    "f84": -3066691,
    "f87": -5.85,
    "f124": 1757057658,
    "f184": 8.95,
    "f204": "-",
    "f205": "-",
    "f206": "-"
  },
  {
    "f1": 2,
    "f2": 32.54,
    "f3": 3.27,
    "f12": "301203",
    "f13": 0,
    "f14": "国泰环保",
    "f62": 4692270,
    "f66": 1494112,
    "f69": 3.06,
    "f72": 3198158,
    "f75": 6.55,
    "f78": -2176913,
    "f81": -4.46,
    "f84": -2515357,
    "f87": -5.15,
    "f124": 1757057700,
    "f184": 9.62,
    "f204": "-",
    "f205": "-",
    "f206": "-"
  },
  {
    "f1": 2,
    "f2": 19.2,
    "f3": 0.58,
    "f12": "603568",
    "f13": 1,
    "f14": "伟明环保",
    "f62": 4501954,
    "f66": -3754528,
    "f69": -3.32,
    "f72": 8256482,
    "f75": 7.3,
    "f78": -5739187,
    "f81": -5.08,
    "f84": 1237233,
    "f87": 1.09,
    "f124": 1757059905,
    "f184": 3.98,
    "f204": "-",
    "f205": "-",
    "f206": "-"
  },
  {
    "f1": 2,
    "f2": 29.16,
    "f3": 3.59,
    "f12": "688370",
    "f13": 1,
    "f14": "丛麟科技",
    "f62": 4418515,
    "f66": -2568927,
    "f69": -3.28,
    "f72": 6987442,
    "f75": 8.93,
    "f78": 5837353,
    "f81": 7.46,
    "f84": -10255868,
    "f87": -13.11,
    "f124": 1757059909,
    "f184": 5.65,
    "f204": "-",
    "f205": "-",
    "f206": "-"
  },
  {
    "f1": 2,
    "f2": 2.78,
    "f3": 1.83,
    "f12": "300266",
    "f13": 0,
    "f14": "兴源环境",
    "f62": 4362540,
    "f66": 0,
    "f69": 0,
    "f72": 4362540,
    "f75": 7.72,
    "f78": -2910771,
    "f81": -5.15,
    "f84": -1451769,
    "f87": -2.57,
    "f124": 1757057664,
    "f184": 7.72,
    "f204": "-",
    "f205": "-",
    "f206": "-"
  },
  {
    "f1": 2,
    "f2": 4.01,
    "f3": -0.5,
    "f12": "002573",
    "f13": 0,
    "f14": "清新环境",
    "f62": 4214777,
    "f66": 1115200,
    "f69": 2.16,
    "f72": 3099577,
    "f75": 6.01,
    "f78": 522060,
    "f81": 1.01,
    "f84": -4736836,
    "f87": -9.18,
    "f124": 1757057649,
    "f184": 8.17,
    "f204": "-",
    "f205": "-",
    "f206": "-"
  },
  {
    "f1": 2,
    "f2": 12.8,
    "f3": 0.95,
    "f12": "300958",
    "f13": 0,
    "f14": "建工修复",
    "f62": 4174901,
    "f66": 1019191,
    "f69": 2.75,
    "f72": 3155710,
    "f75": 8.52,
    "f78": -1259316,
    "f81": -3.4,
    "f84": -2915584,
    "f87": -7.87,
    "f124": 1757057655,
    "f184": 11.27,
    "f204": "-",
    "f205": "-",
    "f206": "-"
  },
  {
    "f1": 2,
    "f2": 7.06,
    "f3": 1.15,
    "f12": "601330",
    "f13": 1,
    "f14": "绿色动力",
    "f62": 3990267,
    "f66": 3339265,
    "f69": 6.3,
    "f72": 651002,
    "f75": 1.23,
    "f78": -1281939,
    "f81": -2.42,
    "f84": -2708328,
    "f87": -5.11,
    "f124": 1757059913,
    "f184": 7.53,
    "f204": "-",
    "f205": "-",
    "f206": "-"
  },
  {
    "f1": 2,
    "f2": 11.36,
    "f3": 2.07,
    "f12": "000551",
    "f13": 0,
    "f14": "创元科技",
    "f62": 3932551,
    "f66": 854721,
    "f69": 1.08,
    "f72": 3077830,
    "f75": 3.9,
    "f78": -1812385,
    "f81": -2.3,
    "f84": -2120166,
    "f87": -2.69,
    "f124": 1757057649,
    "f184": 4.98,
    "f204": "-",
    "f205": "-",
    "f206": "-"
  },
  {
    "f1": 2,
    "f2": 23.62,
    "f3": 1.5,
    "f12": "001230",
    "f13": 0,
    "f14": "劲旅环境",
    "f62": 3738325,
    "f66": 0,
    "f69": 0,
    "f72": 3738325,
    "f75": 8.43,
    "f78": 580141,
    "f81": 1.31,
    "f84": -4318465,
    "f87": -9.74,
    "f124": 1757057673,
    "f184": 8.43,
    "f204": "-",
    "f205": "-",
    "f206": "-"
  },
  {
    "f1": 2,
    "f2": 9.11,
    "f3": 1.9,
    "f12": "600133",
    "f13": 1,
    "f14": "东湖高新",
    "f62": 3672633,
    "f66": 12837369,
    "f69": 7.24,
    "f72": -9164736,
    "f75": -5.17,
    "f78": -2127755,
    "f81": -1.2,
    "f84": -1544878,
    "f87": -0.87,
    "f124": 1757059919,
    "f184": 2.07,
    "f204": "-",
    "f205": "-",
    "f206": "-"
  },
  {
    "f1": 2,
    "f2": 14.91,
    "f3": 0.07,
    "f12": "000885",
    "f13": 0,
    "f14": "城发环境",
    "f62": 3511936,
    "f66": 2431210,
    "f69": 3.48,
    "f72": 1080726,
    "f75": 1.55,
    "f78": 7031958,
    "f81": 10.06,
    "f84": -10543893,
    "f87": -15.08,
    "f124": 1757057667,
    "f184": 5.02,
    "f204": "-",
    "f205": "-",
    "f206": "-"
  },
  {
    "f1": 2,
    "f2": 13.65,
    "f3": 2.02,
    "f12": "688485",
    "f13": 1,
    "f14": "九州一轨",
    "f62": 3412372,
    "f66": 1207869,
    "f69": 3.43,
    "f72": 2204503,
    "f75": 6.26,
    "f78": -2360498,
    "f81": -6.7,
    "f84": -1051875,
    "f87": -2.98,
    "f124": 1757059893,
    "f184": 9.68,
    "f204": "-",
    "f205": "-",
    "f206": "-"
  },
  {
    "f1": 2,
    "f2": 15,
    "f3": 6.31,
    "f12": "301288",
    "f13": 0,
    "f14": "*ST清研",
    "f62": 3064275,
    "f66": -2593734,
    "f69": -7.15,
    "f72": 5658009,
    "f75": 15.6,
    "f78": 1329208,
    "f81": 3.66,
    "f84": -4393483,
    "f87": -12.11,
    "f124": 1757057694,
    "f184": 8.45,
    "f204": "-",
    "f205": "-",
    "f206": "-"
  },
  {
    "f1": 2,
    "f2": 17.24,
    "f3": -0.12,
    "f12": "002034",
    "f13": 0,
    "f14": "旺能环境",
    "f62": 2924847,
    "f66": 0,
    "f69": 0,
    "f72": 2924847,
    "f75": 3.77,
    "f78": 13190241,
    "f81": 17.01,
    "f84": -16115089,
    "f87": -20.79,
    "f124": 1757057679,
    "f184": 3.77,
    "f204": "-",
    "f205": "-",
    "f206": "-"
  },
  {
    "f1": 2,
    "f2": 9.54,
    "f3": 1.6,
    "f12": "300774",
    "f13": 0,
    "f14": "倍杰特",
    "f62": 2383846,
    "f66": 103582,
    "f69": 0.19,
    "f72": 2280264,
    "f75": 4.1,
    "f78": 97029,
    "f81": 0.17,
    "f84": -2480875,
    "f87": -4.46,
    "f124": 1757057679,
    "f184": 4.29,
    "f204": "-",
    "f205": "-",
    "f206": "-"
  },
  {
    "f1": 2,
    "f2": 2.8,
    "f3": 1.82,
    "f12": "300152",
    "f13": 0,
    "f14": "ST新动力",
    "f62": 2360984,
    "f66": 0,
    "f69": 0,
    "f72": 2360984,
    "f75": 4.51,
    "f78": -1166597,
    "f81": -2.23,
    "f84": -1194387,
    "f87": -2.28,
    "f124": 1757057649,
    "f184": 4.51,
    "f204": "-",
    "f205": "-",
    "f206": "-"
  },
  {
    "f1": 2,
    "f2": 6.67,
    "f3": 2.14,
    "f12": "603588",
    "f13": 1,
    "f14": "高能环境",
    "f62": 2308499,
    "f66": 11968423,
    "f69": 6.05,
    "f72": -9659924,
    "f75": -4.89,
    "f78": -11339569,
    "f81": -5.74,
    "f84": 9031071,
    "f87": 4.57,
    "f124": 1757059898,
    "f184": 1.17,
    "f204": "-",
    "f205": "-",
    "f206": "-"
  },
  {
    "f1": 2,
    "f2": 12.53,
    "f3": 0.8,
    "f12": "688057",
    "f13": 1,
    "f14": "金达莱",
    "f62": 2240558,
    "f66": 2121575,
    "f69": 7.42,
    "f72": 118983,
    "f75": 0.42,
    "f78": -3156239,
    "f81": -11.04,
    "f84": 915681,
    "f87": 3.2,
    "f124": 1757059914,
    "f184": 7.84,
    "f204": "-",
    "f205": "-",
    "f206": "-"
  },
  {
    "f1": 2,
    "f2": 15.91,
    "f3": 2.98,
    "f12": "836263",
    "f13": 0,
    "f14": "中航泰达",
    "f62": 2195740,
    "f66": 0,
    "f69": 0,
    "f72": 2195740,
    "f75": 2.79,
    "f78": 2655478,
    "f81": 3.38,
    "f84": 1241053,
    "f87": 1.58,
    "f124": 1757057712,
    "f184": 2.79,
    "f204": "-",
    "f205": "-",
    "f206": "-"
  },
  {
    "f1": 2,
    "f2": 4.61,
    "f3": 0.66,
    "f12": "603797",
    "f13": 1,
    "f14": "联泰环保",
    "f62": 1667724,
    "f66": 381546,
    "f69": 1.42,
    "f72": 1286178,
    "f75": 4.78,
    "f78": -1349382,
    "f81": -5.01,
    "f84": -318342,
    "f87": -1.18,
    "f124": 1757059894,
    "f184": 6.2,
    "f204": "-",
    "f205": "-",
    "f206": "-"
  },
  {
    "f1": 2,
    "f2": 49.71,
    "f3": 8.54,
    "f12": "688376",
    "f13": 1,
    "f14": "美埃科技",
    "f62": 1506841,
    "f66": -1990821,
    "f69": -1.25,
    "f72": 3497662,
    "f75": 2.2,
    "f78": -14791297,
    "f81": -9.31,
    "f84": 13284456,
    "f87": 8.36,
    "f124": 1757059894,
    "f184": 0.95,
    "f204": "-",
    "f205": "-",
    "f206": "-"
  },
  {
    "f1": 2,
    "f2": 10.77,
    "f3": 1.32,
    "f12": "300929",
    "f13": 0,
    "f14": "华骐环保",
    "f62": 1459671,
    "f66": 1203085,
    "f69": 2.95,
    "f72": 256586,
    "f75": 0.63,
    "f78": 1011795,
    "f81": 2.48,
    "f84": -2471465,
    "f87": -6.06,
    "f124": 1757057694,
    "f184": 3.58,
    "f204": "-",
    "f205": "-",
    "f206": "-"
  },
  {
    "f1": 2,
    "f2": 10.49,
    "f3": 2.24,
    "f12": "300210",
    "f13": 0,
    "f14": "森远股份",
    "f62": 1430829,
    "f66": -2835089,
    "f69": -3.49,
    "f72": 4265918,
    "f75": 5.25,
    "f78": -1644334,
    "f81": -2.02,
    "f84": 213505,
    "f87": 0.26,
    "f124": 1757057685,
    "f184": 1.76,
    "f204": "-",
    "f205": "-",
    "f206": "-"
  },
  {
    "f1": 2,
    "f2": 5.23,
    "f3": 0.97,
    "f12": "300385",
    "f13": 0,
    "f14": "雪浪环境",
    "f62": 1388719,
    "f66": 144594,
    "f69": 0.37,
    "f72": 1244125,
    "f75": 3.16,
    "f78": 1143821,
    "f81": 2.91,
    "f84": -2532540,
    "f87": -6.44,
    "f124": 1757057697,
    "f184": 3.53,
    "f204": "-",
    "f205": "-",
    "f206": "-"
  },
  {
    "f1": 2,
    "f2": 20.28,
    "f3": 0.65,
    "f12": "300864",
    "f13": 0,
    "f14": "南大环境",
    "f62": 1333911,
    "f66": 0,
    "f69": 0,
    "f72": 1333911,
    "f75": 6.87,
    "f78": -1277407,
    "f81": -6.58,
    "f84": -56504,
    "f87": -0.29,
    "f124": 1757057667,
    "f184": 6.87,
    "f204": "-",
    "f205": "-",
    "f206": "-"
  },
  {
    "f1": 2,
    "f2": 5.37,
    "f3": 1.32,
    "f12": "300172",
    "f13": 0,
    "f14": "中电环保",
    "f62": 1322011,
    "f66": 7253385,
    "f69": 9.98,
    "f72": -5931374,
    "f75": -8.16,
    "f78": -2020719,
    "f81": -2.78,
    "f84": 698708,
    "f87": 0.96,
    "f124": 1757057685,
    "f184": 1.82,
    "f204": "-",
    "f205": "-",
    "f206": "-"
  },
  {
    "f1": 2,
    "f2": 5.24,
    "f3": 0.58,
    "f12": "002479",
    "f13": 0,
    "f14": "富春环保",
    "f62": 1051361,
    "f66": 1291105,
    "f69": 2.4,
    "f72": -239744,
    "f75": -0.45,
    "f78": 1807937,
    "f81": 3.36,
    "f84": -2859298,
    "f87": -5.31,
    "f124": 1757057691,
    "f184": 1.95,
    "f204": "-",
    "f205": "-",
    "f206": "-"
  },
  {
    "f1": 2,
    "f2": 4.66,
    "f3": 2.19,
    "f12": "000035",
    "f13": 0,
    "f14": "中国天楹",
    "f62": 1032937,
    "f66": -12002151,
    "f69": -6.16,
    "f72": 13035088,
    "f75": 6.69,
    "f78": 7830896,
    "f81": 4.02,
    "f84": -8863833,
    "f87": -4.55,
    "f124": 1757057646,
    "f184": 0.53,
    "f204": "-",
    "f205": "-",
    "f206": "-"
  },
  {
    "f1": 2,
    "f2": 10.65,
    "f3": 2.4,
    "f12": "688659",
    "f13": 1,
    "f14": "元琛科技",
    "f62": 913001,
    "f66": 1744066,
    "f69": 3.91,
    "f72": -831065,
    "f75": -1.86,
    "f78": 1397955,
    "f81": 3.13,
    "f84": -2310956,
    "f87": -5.18,
    "f124": 1757059902,
    "f184": 2.05,
    "f204": "-",
    "f205": "-",
    "f206": "-"
  },
  {
    "f1": 2,
    "f2": 4.38,
    "f3": 0.23,
    "f12": "600217",
    "f13": 1,
    "f14": "中再资环",
    "f62": 526017,
    "f66": 1754418,
    "f69": 3.58,
    "f72": -1228401,
    "f75": -2.51,
    "f78": -2753599,
    "f81": -5.62,
    "f84": 2227582,
    "f87": 4.55,
    "f124": 1757059922,
    "f184": 1.07,
    "f204": "-",
    "f205": "-",
    "f206": "-"
  },
  {
    "f1": 2,
    "f2": 24.98,
    "f3": 2.42,
    "f12": "301148",
    "f13": 0,
    "f14": "嘉戎技术",
    "f62": 316254,
    "f66": 0,
    "f69": 0,
    "f72": 316254,
    "f75": 0.93,
    "f78": 1801726,
    "f81": 5.29,
    "f84": -2117980,
    "f87": -6.21,
    "f124": 1757057667,
    "f184": 0.93,
    "f204": "-",
    "f205": "-",
    "f206": "-"
  },
  {
    "f1": 2,
    "f2": 11.55,
    "f3": 0.52,
    "f12": "300800",
    "f13": 0,
    "f14": "力合科技",
    "f62": 128861,
    "f66": 0,
    "f69": 0,
    "f72": 128861,
    "f75": 0.37,
    "f78": 2624270,
    "f81": 7.48,
    "f84": -2753131,
    "f87": -7.84,
    "f124": 1757057682,
    "f184": 0.37,
    "f204": "-",
    "f205": "-",
    "f206": "-"
  },
  {
    "f1": 2,
    "f2": "-",
    "f3": "-",
    "f12": "603359",
    "f13": 1,
    "f14": "东珠生态",
    "f62": "-",
    "f66": "-",
    "f69": "-",
    "f72": "-",
    "f75": "-",
    "f78": "-",
    "f81": "-",
    "f84": "-",
    "f87": "-",
    "f124": 1757059906,
    "f184": "-",
    "f204": "-",
    "f205": "-",
    "f206": "-"
  },
  {
    "f1": 2,
    "f2": "-",
    "f3": "-",
    "f12": "000711",
    "f13": 0,
    "f14": "*ST京蓝",
    "f62": "-",
    "f66": "-",
    "f69": "-",
    "f72": "-",
    "f75": "-",
    "f78": "-",
    "f81": "-",
    "f84": "-",
    "f87": "-",
    "f124": 1757057688,
    "f184": "-",
    "f204": "-",
    "f205": "-",
    "f206": "-"
  },
  {
    "f1": 2,
    "f2": 7.1,
    "f3": 0.28,
    "f12": "300334",
    "f13": 0,
    "f14": "津膜科技",
    "f62": -63620,
    "f66": 0,
    "f69": 0,
    "f72": -63620,
    "f75": -0.19,
    "f78": 724965,
    "f81": 2.15,
    "f84": -661345,
    "f87": -1.96,
    "f124": 1757057667,
    "f184": -0.19,
    "f204": "-",
    "f205": "-",
    "f206": "-"
  },
  {
    "f1": 2,
    "f2": 15.98,
    "f3": -1.05,
    "f12": "688679",
    "f13": 1,
    "f14": "通源环境",
    "f62": -74013,
    "f66": -3262156,
    "f69": -7.49,
    "f72": 3188143,
    "f75": 7.32,
    "f78": 1548961,
    "f81": 3.56,
    "f84": -1474948,
    "f87": -3.39,
    "f124": 1757059913,
    "f184": -0.17,
    "f204": "-",
    "f205": "-",
    "f206": "-"
  },
  {
    "f1": 2,
    "f2": 10.25,
    "f3": 2.91,
    "f12": "688565",
    "f13": 1,
    "f14": "力源科技",
    "f62": -126862,
    "f66": 2586,
    "f69": 0.01,
    "f72": -129448,
    "f75": -0.36,
    "f78": 979712,
    "f81": 2.73,
    "f84": -852850,
    "f87": -2.38,
    "f124": 1757059908,
    "f184": -0.35,
    "f204": "-",
    "f205": "-",
    "f206": "-"
  },
  {
    "f1": 2,
    "f2": 20.73,
    "f3": 1.42,
    "f12": "301305",
    "f13": 0,
    "f14": "朗坤科技",
    "f62": -137473,
    "f66": 519666,
    "f69": 0.38,
    "f72": -657139,
    "f75": -0.49,
    "f78": 7373993,
    "f81": 5.44,
    "f84": -7236520,
    "f87": -5.34,
    "f124": 1757057685,
    "f184": -0.1,
    "f204": "-",
    "f205": "-",
    "f206": "-"
  },
  {
    "f1": 2,
    "f2": 19.44,
    "f3": 2.05,
    "f12": "003027",
    "f13": 0,
    "f14": "同兴科技",
    "f62": -210601,
    "f66": 0,
    "f69": 0,
    "f72": -210601,
    "f75": -0.34,
    "f78": 3224039,
    "f81": 5.17,
    "f84": -3013437,
    "f87": -4.83,
    "f124": 1757057694,
    "f184": -0.34,
    "f204": "-",
    "f205": "-",
    "f206": "-"
  },
  {
    "f1": 2,
    "f2": 5.77,
    "f3": 0.87,
    "f12": "600796",
    "f13": 1,
    "f14": "钱江生化",
    "f62": -233423,
    "f66": 27853,
    "f69": 0.09,
    "f72": -261276,
    "f75": -0.83,
    "f78": -1578972,
    "f81": -5.01,
    "f84": 1812395,
    "f87": 5.76,
    "f124": 1757059903,
    "f184": -0.74,
    "f204": "-",
    "f205": "-",
    "f206": "-"
  },
  {
    "f1": 2,
    "f2": 11.18,
    "f3": 1.54,
    "f12": "301265",
    "f13": 0,
    "f14": "华新环保",
    "f62": -357533,
    "f66": 0,
    "f69": 0,
    "f72": -357533,
    "f75": -0.8,
    "f78": -621279,
    "f81": -1.4,
    "f84": 978812,
    "f87": 2.2,
    "f124": 1757057676,
    "f184": -0.8,
    "f204": "-",
    "f205": "-",
    "f206": "-"
  },
  {
    "f1": 2,
    "f2": 17.1,
    "f3": 1,
    "f12": "300867",
    "f13": 0,
    "f14": "圣元环保",
    "f62": -423796,
    "f66": -4641239,
    "f69": -6.96,
    "f72": 4217443,
    "f75": 6.33,
    "f78": 1340899,
    "f81": 2.01,
    "f84": -917103,
    "f87": -1.38,
    "f124": 1757057649,
    "f184": -0.64,
    "f204": "-",
    "f205": "-",
    "f206": "-"
  },
  {
    "f1": 2,
    "f2": 26.5,
    "f3": 1.53,
    "f12": "301372",
    "f13": 0,
    "f14": "科净源",
    "f62": -443159,
    "f66": 2304113,
    "f69": 6.62,
    "f72": -2747272,
    "f75": -7.89,
    "f78": 1653092,
    "f81": 4.75,
    "f84": -1209932,
    "f87": -3.48,
    "f124": 1757057655,
    "f184": -1.27,
    "f204": "-",
    "f205": "-",
    "f206": "-"
  },
  {
    "f1": 2,
    "f2": 7.04,
    "f3": 3.07,
    "f12": "300137",
    "f13": 0,
    "f14": "ST先河",
    "f62": -463704,
    "f66": 1008424,
    "f69": 1.48,
    "f72": -1472128,
    "f75": -2.16,
    "f78": 3234390,
    "f81": 4.75,
    "f84": -2770686,
    "f87": -4.07,
    "f124": 1757057682,
    "f184": -0.68,
    "f204": "-",
    "f205": "-",
    "f206": "-"
  },
  {
    "f1": 2,
    "f2": 11.1,
    "f3": 0.91,
    "f12": "300948",
    "f13": 0,
    "f14": "冠中生态",
    "f62": -504063,
    "f66": 0,
    "f69": 0,
    "f72": -504063,
    "f75": -1.27,
    "f78": 384143,
    "f81": 0.97,
    "f84": 119920,
    "f87": 0.3,
    "f124": 1757057676,
    "f184": -1.27,
    "f204": "-",
    "f205": "-",
    "f206": "-"
  },
  {
    "f1": 2,
    "f2": 2.61,
    "f3": -0.76,
    "f12": "000820",
    "f13": 0,
    "f14": "*ST节能",
    "f62": -533117,
    "f66": 0,
    "f69": 0,
    "f72": -533117,
    "f75": -3.41,
    "f78": -989047,
    "f81": -6.33,
    "f84": 1522165,
    "f87": 9.75,
    "f124": 1757057691,
    "f184": -3.41,
    "f204": "-",
    "f205": "-",
    "f206": "-"
  },
  {
    "f1": 2,
    "f2": 46.68,
    "f3": 3.16,
    "f12": "688480",
    "f13": 1,
    "f14": "赛恩斯",
    "f62": -572998,
    "f66": -256025,
    "f69": -0.79,
    "f72": -316973,
    "f75": -0.98,
    "f78": 976058,
    "f81": 3.01,
    "f84": -403059,
    "f87": -1.24,
    "f124": 1757059904,
    "f184": -1.77,
    "f204": "-",
    "f205": "-",
    "f206": "-"
  },
  {
    "f1": 2,
    "f2": 15.01,
    "f3": 2.81,
    "f12": "688335",
    "f13": 1,
    "f14": "复洁环保",
    "f62": -611618,
    "f66": -1130034,
    "f69": -4.09,
    "f72": 518416,
    "f75": 1.88,
    "f78": 1721777,
    "f81": 6.23,
    "f84": -1110159,
    "f87": -4.02,
    "f124": 1757059893,
    "f184": -2.21,
    "f204": "-",
    "f205": "-",
    "f206": "-"
  },
  {
    "f1": 2,
    "f2": 25.07,
    "f3": 4.68,
    "f12": "688178",
    "f13": 1,
    "f14": "万德斯",
    "f62": -619462,
    "f66": -2325829,
    "f69": -5.89,
    "f72": 1706367,
    "f75": 4.32,
    "f78": 4158459,
    "f81": 10.53,
    "f84": -3538996,
    "f87": -8.96,
    "f124": 1757059896,
    "f184": -1.57,
    "f204": "-",
    "f205": "-",
    "f206": "-"
  },
  {
    "f1": 2,
    "f2": 10.24,
    "f3": 1.29,
    "f12": "301081",
    "f13": 0,
    "f14": "严牌股份",
    "f62": -624770,
    "f66": 1112064,
    "f69": 3.7,
    "f72": -1736834,
    "f75": -5.78,
    "f78": -1318101,
    "f81": -4.39,
    "f84": 1942871,
    "f87": 6.47,
    "f124": 1757057673,
    "f184": -2.08,
    "f204": "-",
    "f205": "-",
    "f206": "-"
  },
  {
    "f1": 2,
    "f2": 16.61,
    "f3": 1.78,
    "f12": "688101",
    "f13": 1,
    "f14": "三达膜",
    "f62": -886459,
    "f66": 1812825,
    "f69": 1.5,
    "f72": -2699284,
    "f75": -2.23,
    "f78": 11410547,
    "f81": 9.44,
    "f84": -10524088,
    "f87": -8.71,
    "f124": 1757059912,
    "f184": -0.73,
    "f204": "-",
    "f205": "-",
    "f206": "-"
  },
  {
    "f1": 2,
    "f2": 5.49,
    "f3": 1.29,
    "f12": "300664",
    "f13": 0,
    "f14": "鹏鹞环保",
    "f62": -888511,
    "f66": 2694234,
    "f69": 6.38,
    "f72": -3582745,
    "f75": -8.49,
    "f78": 2351435,
    "f81": 5.57,
    "f84": -1462924,
    "f87": -3.47,
    "f124": 1757057667,
    "f184": -2.11,
    "f204": "-",
    "f205": "-",
    "f206": "-"
  },
  {
    "f1": 2,
    "f2": 4.56,
    "f3": 2.47,
    "f12": "300355",
    "f13": 0,
    "f14": "蒙草生态",
    "f62": -912903,
    "f66": -3196022,
    "f69": -1.57,
    "f72": 2283119,
    "f75": 1.12,
    "f78": -3801704,
    "f81": -1.87,
    "f84": 4714607,
    "f87": 2.32,
    "f124": 1757057664,
    "f184": -0.45,
    "f204": "-",
    "f205": "-",
    "f206": "-"
  },
  {
    "f1": 2,
    "f2": 18.53,
    "f3": 2.21,
    "f12": "688021",
    "f13": 1,
    "f14": "奥福科技",
    "f62": -940343,
    "f66": 0,
    "f69": 0,
    "f72": -940343,
    "f75": -3.73,
    "f78": 926687,
    "f81": 3.67,
    "f84": 13656,
    "f87": 0.05,
    "f124": 1757059895,
    "f184": -3.73,
    "f204": "-",
    "f205": "-",
    "f206": "-"
  },
  {
    "f1": 2,
    "f2": 28.2,
    "f3": 1.11,
    "f12": "300899",
    "f13": 0,
    "f14": "*ST凯鑫",
    "f62": -1133663,
    "f66": -25128,
    "f69": -0.1,
    "f72": -1108535,
    "f75": -4.38,
    "f78": 2605614,
    "f81": 10.3,
    "f84": -1471950,
    "f87": -5.82,
    "f124": 1757057694,
    "f184": -4.48,
    "f204": "-",
    "f205": "-",
    "f206": "-"
  },
  {
    "f1": 2,
    "f2": 5.21,
    "f3": 0.97,
    "f12": "300187",
    "f13": 0,
    "f14": "永清环保",
    "f62": -1203106,
    "f66": 0,
    "f69": 0,
    "f72": -1203106,
    "f75": -4.06,
    "f78": -1339551,
    "f81": -4.52,
    "f84": 2542657,
    "f87": 8.58,
    "f124": 1757057646,
    "f184": -4.06,
    "f204": "-",
    "f205": "-",
    "f206": "-"
  },
  {
    "f1": 2,
    "f2": 4.85,
    "f3": -0.41,
    "f12": "002672",
    "f13": 0,
    "f14": "东江环保",
    "f62": -1217323,
    "f66": -1101490,
    "f69": -3.14,
    "f72": -115833,
    "f75": -0.33,
    "f78": 4640206,
    "f81": 13.21,
    "f84": -3422883,
    "f87": -9.75,
    "f124": 1757057685,
    "f184": -3.47,
    "f204": "-",
    "f205": "-",
    "f206": "-"
  },
  {
    "f1": 2,
    "f2": 8.62,
    "f3": 1.77,
    "f12": "688701",
    "f13": 1,
    "f14": "卓锦股份",
    "f62": -1224838,
    "f66": 0,
    "f69": 0,
    "f72": -1224838,
    "f75": -4.96,
    "f78": 2301441,
    "f81": 9.32,
    "f84": -1076604,
    "f87": -4.36,
    "f124": 1757059894,
    "f184": -4.96,
    "f204": "-",
    "f205": "-",
    "f206": "-"
  },
  {
    "f1": 2,
    "f2": 13.23,
    "f3": -0.45,
    "f12": "605081",
    "f13": 1,
    "f14": "*ST太和",
    "f62": -1343894,
    "f66": -2350413,
    "f69": -13.06,
    "f72": 1006519,
    "f75": 5.59,
    "f78": 475367,
    "f81": 2.64,
    "f84": 868526,
    "f87": 4.83,
    "f124": 1757059921,
    "f184": -7.47,
    "f204": "-",
    "f205": "-",
    "f206": "-"
  },
  {
    "f1": 2,
    "f2": 21.9,
    "f3": 1.86,
    "f12": "301049",
    "f13": 0,
    "f14": "超越科技",
    "f62": -1389045,
    "f66": 285211,
    "f69": 0.83,
    "f72": -1674256,
    "f75": -4.86,
    "f78": 1853187,
    "f81": 5.38,
    "f84": -464142,
    "f87": -1.35,
    "f124": 1757057700,
    "f184": -4.03,
    "f204": "-",
    "f205": "-",
    "f206": "-"
  },
  {
    "f1": 2,
    "f2": 8.6,
    "f3": 0.12,
    "f12": "601827",
    "f13": 1,
    "f14": "三峰环境",
    "f62": -1414837,
    "f66": -4413676,
    "f69": -6.37,
    "f72": 2998839,
    "f75": 4.33,
    "f78": 4412111,
    "f81": 6.37,
    "f84": -2997275,
    "f87": -4.33,
    "f124": 1757059920,
    "f184": -2.04,
    "f204": "-",
    "f205": "-",
    "f206": "-"
  },
  {
    "f1": 2,
    "f2": 21.2,
    "f3": 1,
    "f12": "688069",
    "f13": 1,
    "f14": "德林海",
    "f62": -1670035,
    "f66": 1499715,
    "f69": 3.75,
    "f72": -3169750,
    "f75": -7.93,
    "f78": -3065330,
    "f81": -7.67,
    "f84": 4735363,
    "f87": 11.84,
    "f124": 1757059909,
    "f184": -4.18,
    "f204": "-",
    "f205": "-",
    "f206": "-"
  },
  {
    "f1": 2,
    "f2": 5.46,
    "f3": 0.74,
    "f12": "301175",
    "f13": 0,
    "f14": "中科环保",
    "f62": -2136330,
    "f66": -4368918,
    "f69": -4.1,
    "f72": 2232588,
    "f75": 2.1,
    "f78": -883990,
    "f81": -0.83,
    "f84": 3020321,
    "f87": 2.84,
    "f124": 1757057691,
    "f184": -2.01,
    "f204": "-",
    "f205": "-",
    "f206": "-"
  },
  {
    "f1": 2,
    "f2": 2.26,
    "f3": 2.26,
    "f12": "300197",
    "f13": 0,
    "f14": "节能铁汉",
    "f62": -2404056,
    "f66": 0,
    "f69": 0,
    "f72": -2404056,
    "f75": -1.6,
    "f78": -2863091,
    "f81": -1.91,
    "f84": 5267146,
    "f87": 3.51,
    "f124": 1757057652,
    "f184": -1.6,
    "f204": "-",
    "f205": "-",
    "f206": "-"
  },
  {
    "f1": 2,
    "f2": 17.08,
    "f3": 0.29,
    "f12": "300961",
    "f13": 0,
    "f14": "深水海纳",
    "f62": -2795161,
    "f66": -2994366,
    "f69": -2.46,
    "f72": 199205,
    "f75": 0.16,
    "f78": -619516,
    "f81": -0.51,
    "f84": 3414678,
    "f87": 2.8,
    "f124": 1757057697,
    "f184": -2.29,
    "f204": "-",
    "f205": "-",
    "f206": "-"
  },
  {
    "f1": 2,
    "f2": 5.13,
    "f3": -0.77,
    "f12": "600526",
    "f13": 1,
    "f14": "菲达环保",
    "f62": -3591750,
    "f66": -8567053,
    "f69": -9.14,
    "f72": 4975303,
    "f75": 5.31,
    "f78": 3415871,
    "f81": 3.64,
    "f84": 175879,
    "f87": 0.19,
    "f124": 1757059897,
    "f184": -3.83,
    "f204": "-",
    "f205": "-",
    "f206": "-"
  },
  {
    "f1": 2,
    "f2": 4.46,
    "f3": 1.13,
    "f12": "300070",
    "f13": 0,
    "f14": "碧水源",
    "f62": -3595776,
    "f66": -1415389,
    "f69": -1.13,
    "f72": -2180387,
    "f75": -1.74,
    "f78": 984572,
    "f81": 0.79,
    "f84": 2611205,
    "f87": 2.09,
    "f124": 1757057658,
    "f184": -2.88,
    "f204": "-",
    "f205": "-",
    "f206": "-"
  },
  {
    "f1": 2,
    "f2": 3.78,
    "f3": 0,
    "f12": "000068",
    "f13": 0,
    "f14": "华控赛格",
    "f62": -4849313,
    "f66": -7382054,
    "f69": -8.83,
    "f72": 2532741,
    "f75": 3.03,
    "f78": 1483241,
    "f81": 1.77,
    "f84": 3366072,
    "f87": 4.03,
    "f124": 1757057658,
    "f184": -5.8,
    "f204": "-",
    "f205": "-",
    "f206": "-"
  },
  {
    "f1": 2,
    "f2": 10.6,
    "f3": 1.53,
    "f12": "600539",
    "f13": 1,
    "f14": "狮头股份",
    "f62": -5386746,
    "f66": 2269950,
    "f69": 2.92,
    "f72": -7656696,
    "f75": -9.84,
    "f78": -1138227,
    "f81": -1.46,
    "f84": 6524972,
    "f87": 8.39,
    "f124": 1757059897,
    "f184": -6.92,
    "f204": "-",
    "f205": "-",
    "f206": "-"
  },
  {
    "f1": 2,
    "f2": 19.98,
    "f3": 0.96,
    "f12": "300854",
    "f13": 0,
    "f14": "中兰环保",
    "f62": -5631832,
    "f66": -829044,
    "f69": -1.12,
    "f72": -4802788,
    "f75": -6.47,
    "f78": 6260317,
    "f81": 8.44,
    "f84": -628485,
    "f87": -0.85,
    "f124": 1757057670,
    "f184": -7.59,
    "f204": "-",
    "f205": "-",
    "f206": "-"
  },
  {
    "f1": 2,
    "f2": 27.25,
    "f3": 0.52,
    "f12": "301068",
    "f13": 0,
    "f14": "大地海洋",
    "f62": -6317970,
    "f66": -1301202,
    "f69": -4.48,
    "f72": -5016768,
    "f75": -17.28,
    "f78": 3768567,
    "f81": 12.98,
    "f84": 2549404,
    "f87": 8.78,
    "f124": 1757057655,
    "f184": -21.77,
    "f204": "-",
    "f205": "-",
    "f206": "-"
  },
  {
    "f1": 2,
    "f2": 5.4,
    "f3": 1.12,
    "f12": "300422",
    "f13": 0,
    "f14": "博世科",
    "f62": -6781026,
    "f66": -4020844,
    "f69": -5.06,
    "f72": -2760182,
    "f75": -3.47,
    "f78": -2529851,
    "f81": -3.18,
    "f84": 9310878,
    "f87": 11.72,
    "f124": 1757057685,
    "f184": -8.53,
    "f204": "-",
    "f205": "-",
    "f206": "-"
  },
  {
    "f1": 2,
    "f2": 16.25,
    "f3": 3.31,
    "f12": "301500",
    "f13": 0,
    "f14": "飞南资源",
    "f62": -6937647,
    "f66": -1192297,
    "f69": -0.97,
    "f72": -5745350,
    "f75": -4.7,
    "f78": -5369455,
    "f81": -4.39,
    "f84": 12307102,
    "f87": 10.06,
    "f124": 1757057703,
    "f184": -5.67,
    "f204": "-",
    "f205": "-",
    "f206": "-"
  },
  {
    "f1": 2,
    "f2": 2.13,
    "f3": 0.47,
    "f12": "000826",
    "f13": 0,
    "f14": "启迪环境",
    "f62": -7522252,
    "f66": -3001013,
    "f69": -1.69,
    "f72": -4521239,
    "f75": -2.55,
    "f78": 25267,
    "f81": 0.01,
    "f84": 7496985,
    "f87": 4.23,
    "f124": 1757057694,
    "f184": -4.24,
    "f204": "-",
    "f205": "-",
    "f206": "-"
  },
  {
    "f1": 2,
    "f2": 14.96,
    "f3": 1.15,
    "f12": "301109",
    "f13": 0,
    "f14": "军信股份",
    "f62": -7976652,
    "f66": 1690435,
    "f69": 1.7,
    "f72": -9667087,
    "f75": -9.7,
    "f78": 3653832,
    "f81": 3.67,
    "f84": 4322819,
    "f87": 4.34,
    "f124": 1757057658,
    "f184": -8,
    "f204": "-",
    "f205": "-",
    "f206": "-"
  },
  {
    "f1": 2,
    "f2": 12.64,
    "f3": 0.16,
    "f12": "600388",
    "f13": 1,
    "f14": "龙净环保",
    "f62": -8002344,
    "f66": -5109273,
    "f69": -2.95,
    "f72": -2893071,
    "f75": -1.67,
    "f78": 8609312,
    "f81": 4.98,
    "f84": -606968,
    "f87": -0.35,
    "f124": 1757059898,
    "f184": -4.63,
    "f204": "-",
    "f205": "-",
    "f206": "-"
  },
  {
    "f1": 2,
    "f2": 1.68,
    "f3": -0.59,
    "f12": "002717",
    "f13": 0,
    "f14": "ST岭南",
    "f62": -9352219,
    "f66": -3067450,
    "f69": -3.11,
    "f72": -6284769,
    "f75": -6.37,
    "f78": 590692,
    "f81": 0.6,
    "f84": 8761527,
    "f87": 8.88,
    "f124": 1757057682,
    "f184": -9.48,
    "f204": "-",
    "f205": "-",
    "f206": "-"
  },
  {
    "f1": 2,
    "f2": 8.7,
    "f3": 0,
    "f12": "688096",
    "f13": 1,
    "f14": "京源环保",
    "f62": -9670196,
    "f66": -923463,
    "f69": -1.48,
    "f72": -8746733,
    "f75": -14.01,
    "f78": 9936513,
    "f81": 15.91,
    "f84": -266317,
    "f87": -0.43,
    "f124": 1757059907,
    "f184": -15.49,
    "f204": "-",
    "f205": "-",
    "f206": "-"
  },
  {
    "f1": 2,
    "f2": 26.39,
    "f3": 4.06,
    "f12": "300815",
    "f13": 0,
    "f14": "玉禾田",
    "f62": -9986109,
    "f66": -609025,
    "f69": -0.15,
    "f72": -9377084,
    "f75": -2.31,
    "f78": -26766232,
    "f81": -6.58,
    "f84": 36752342,
    "f87": 9.04,
    "f124": 1757057700,
    "f184": -2.46,
    "f204": "-",
    "f205": "-",
    "f206": "-"
  },
  {
    "f1": 2,
    "f2": 5.9,
    "f3": 0.17,
    "f12": "300055",
    "f13": 0,
    "f14": "万邦达",
    "f62": -10414850,
    "f66": -1934577,
    "f69": -3.24,
    "f72": -8480273,
    "f75": -14.18,
    "f78": 7461603,
    "f81": 12.48,
    "f84": 2953247,
    "f87": 4.94,
    "f124": 1757057661,
    "f184": -17.42,
    "f204": "-",
    "f205": "-",
    "f206": "-"
  },
  {
    "f1": 2,
    "f2": 21.04,
    "f3": -0.99,
    "f12": "688466",
    "f13": 1,
    "f14": "金科环境",
    "f62": -11294729,
    "f66": -7999104,
    "f69": -23.12,
    "f72": -3295625,
    "f75": -9.52,
    "f78": 4429562,
    "f81": 12.8,
    "f84": 6865167,
    "f87": 19.84,
    "f124": 1757059916,
    "f184": -32.64,
    "f204": "-",
    "f205": "-",
    "f206": "-"
  },
  {
    "f1": 2,
    "f2": 16.39,
    "f3": 0.55,
    "f12": "601033",
    "f13": 1,
    "f14": "永兴股份",
    "f62": -11570437,
    "f66": -8399702,
    "f69": -7.33,
    "f72": -3170735,
    "f75": -2.77,
    "f78": 5417386,
    "f81": 4.73,
    "f84": 6153051,
    "f87": 5.37,
    "f124": 1757059898,
    "f184": -10.09,
    "f204": "-",
    "f205": "-",
    "f206": "-"
  },
  {
    "f1": 2,
    "f2": 6.53,
    "f3": -1.95,
    "f12": "603817",
    "f13": 1,
    "f14": "海峡环保",
    "f62": -12791491,
    "f66": 4010835,
    "f69": 0.88,
    "f72": -16802326,
    "f75": -3.68,
    "f78": 19137725,
    "f81": 4.19,
    "f84": -6346234,
    "f87": -1.39,
    "f124": 1757059900,
    "f184": -2.8,
    "f204": "-",
    "f205": "-",
    "f206": "-"
  },
  {
    "f1": 2,
    "f2": 24.84,
    "f3": -2.51,
    "f12": "688309",
    "f13": 1,
    "f14": "恒誉环保",
    "f62": -22292416,
    "f66": -5594476,
    "f69": -7.63,
    "f72": -16697940,
    "f75": -22.77,
    "f78": 9087501,
    "f81": 12.39,
    "f84": 13204914,
    "f87": 18.01,
    "f124": 1757059899,
    "f184": -30.4,
    "f204": "-",
    "f205": "-",
    "f206": "-"
  },
  {
    "f1": 2,
    "f2": 45.05,
    "f3": -4.56,
    "f12": "301259",
    "f13": 0,
    "f14": "艾布鲁",
    "f62": -28675822,
    "f66": -14614595,
    "f69": -2.32,
    "f72": -14061227,
    "f75": -2.23,
    "f78": 17055194,
    "f81": 2.7,
    "f84": 11620627,
    "f87": 1.84,
    "f124": 1757057661,
    "f184": -4.54,
    "f204": "-",
    "f205": "-",
    "f206": "-"
  },
  {
    "f1": 2,
    "f2": 15.95,
    "f3": 2.84,
    "f12": "300786",
    "f13": 0,
    "f14": "国林科技",
    "f62": -31464657,
    "f66": -2646225,
    "f69": -1.12,
    "f72": -28818432,
    "f75": -12.2,
    "f78": -35652629,
    "f81": -15.09,
    "f84": 67117287,
    "f87": 28.41,
    "f124": 1757057670,
    "f184": -13.32,
    "f204": "-",
    "f205": "-",
    "f206": "-"
  },
  {
    "f1": 2,
    "f2": 19.17,
    "f3": 1.05,
    "f12": "603686",
    "f13": 1,
    "f14": "福龙马",
    "f62": -40471739,
    "f66": -10904456,
    "f69": -1.77,
    "f72": -29567283,
    "f75": -4.8,
    "f78": 22767301,
    "f81": 3.7,
    "f84": 17704438,
    "f87": 2.87,
    "f124": 1757059913,
    "f184": -6.57,
    "f204": "-",
    "f205": "-",
    "f206": "-"
  },
  {
    "f1": 2,
    "f2": 3.56,
    "f3": -10.1,
    "f12": "002210",
    "f13": 0,
    "f14": "飞马国际",
    "f62": -338525921,
    "f66": -403777281,
    "f69": -23.04,
    "f72": 65251360,
    "f75": 3.72,
    "f78": 116759824,
    "f81": 6.66,
    "f84": 221766112,
    "f87": 12.66,
    "f124": 1757057673,
    "f184": -19.32,
    "f204": "-",
    "f205": "-",
    "f206": "-"
  }
]
