{
  "rc": 0,
  "rt": 114,
  "svr": 177618785,
  "lt": 2,
  "full": 0,
  "data": {
    "tc": 18,
    "qdate": 20260402,
    "pool": [
      {
        "c": "600249",
        "m": 1,
        "n": "两面针",
        "p": 7140,
        "ztp": 7710,
        "zdp": 1.8544936180114746,
        "amount": 945112384,
        "ltsz": 3927000000,
        "tshare": 3927000000,
        "hs": 23.284786224365234,
        "fbt": 92501,
        "zbc": 1,
        "zf": 9.985734939575195,
        "zs": 0.14025245606899261,
        "zttj": {
          "days": 2,
          "ct": 1
        },
        "hybk": "个护用品"
      },
      {
        "c": "002923",
        "m": 0,
        "n": "润都股份",
        "p": 17350,
        "ztp": 18960,
        "zdp": 0.6380510330200195,
        "amount": 1039146304,
        "ltsz": 4477771852.55,
        "tshare": 5810398408,
        "hs": 22.70926856994629,
        "fbt": 93027,
        "zbc": 1,
        "zf": 15.081206321716309,
        "zs": -0.7437070608139038,
        "zttj": {
          "days": 2,
          "ct": 1
        },
        "hybk": "化学制药"
      },
      {
        "c": "000632",
        "m": 0,
        "n": "三木集团",
        "p": 4890,
        "ztp": 5210,
        "zdp": 3.1645569801330566,
        "amount": 413121376,
        "ltsz": 2276205053.3399997,
        "tshare": 2276390687.52,
        "hs": 17.934473037719727,
        "fbt": 93236,
        "zbc": 1,
        "zf": 8.860759735107422,
        "zs": 0,
        "zttj": {
          "days": 0,
          "ct": 0
        },
        "hybk": "综合Ⅱ"
      },
      {
        "c": "600101",
        "m": 1,
        "n": "明星电力",
        "p": 9960,
        "ztp": 10530,
        "zdp": 4.075235366821289,
        "amount": 711959904,
        "ltsz": 5456710211.160001,
        "tshare": 5456710141.440001,
        "hs": 12.802606582641602,
        "fbt": 93330,
        "zbc": 1,
        "zf": 9.508881568908691,
        "zs": 0,
        "zttj": {
          "days": 0,
          "ct": 0
        },
        "hybk": "电力"
      },
      {
        "c": "002471",
        "m": 0,
        "n": "中超控股",
        "p": 9360,
        "ztp": 9700,
        "zdp": 6.122448921203613,
        "amount": 4335369216,
        "ltsz": 12564852421.679998,
        "tshare": 12811593600,
        "hs": 33.893009185791016,
        "fbt": 93609,
        "zbc": 1,
        "zf": 11.224489212036133,
        "zs": -0.10672358423471451,
        "zttj": {
          "days": 0,
          "ct": 0
        },
        "hybk": "电网设备"
      },
      {
        "c": "601872",
        "m": 1,
        "n": "招商轮船",
        "p": 19470,
        "ztp": 19800,
        "zdp": 8.166666030883789,
        "amount": 6428486656,
        "ltsz": 157211264633.94,
        "tshare": 157211264517.12,
        "hs": 4.086767673492432,
        "fbt": 93755,
        "zbc": 8,
        "zf": 9.222222328186035,
        "zs": 0.46439626812934875,
        "zttj": {
          "days": 2,
          "ct": 1
        },
        "hybk": "航运港口"
      },
      {
        "c": "001208",
        "m": 0,
        "n": "华菱线缆",
        "p": 19880,
        "ztp": 20770,
        "zdp": 5.296610355377197,
        "amount": 987101344,
        "ltsz": 5232619710.36,
        "tshare": 12690406588.16,
        "hs": 18.64505386352539,
        "fbt": 94433,
        "zbc": 1,
        "zf": 10.540254592895508,
        "zs": 0,
        "zttj": {
          "days": 0,
          "ct": 0
        },
        "hybk": "电网设备"
      },
      {
        "c": "601869",
        "m": 1,
        "n": "长飞光纤",
        "p": 332490,
        "ztp": 338800,
        "zdp": 7.951298236846924,
        "amount": 6337712640,
        "ltsz": 135103426021.86,
        "tshare": 275270168028.96,
        "hs": 4.728627681732178,
        "fbt": 95321,
        "zbc": 2,
        "zf": 11.00649356842041,
        "zs": 0.29864251613616943,
        "zttj": {
          "days": 0,
          "ct": 0
        },
        "hybk": "通信设备"
      },
      {
        "c": "002273",
        "m": 0,
        "n": "水晶光电",
        "p": 24840,
        "ztp": 25540,
        "zdp": 6.976744651794434,
        "amount": 3257158032,
        "ltsz": 33837342453.36,
        "tshare": 34543304444.159996,
        "hs": 9.548989295959473,
        "fbt": 95621,
        "zbc": 1,
        "zf": 10.93884563446045,
        "zs": 0.16129031777381897,
        "zttj": {
          "days": 0,
          "ct": 0
        },
        "hybk": "光学光电"
      },
      {
        "c": "002890",
        "m": 0,
        "n": "弘宇股份",
        "p": 16470,
        "ztp": 17380,
        "zdp": 4.240506649017334,
        "amount": 160176150,
        "ltsz": 2659644938.7,
        "tshare": 2797843885.2,
        "hs": 5.883478164672852,
        "fbt": 95748,
        "zbc": 1,
        "zf": 10.94936752319336,
        "zs": 0.4881024956703186,
        "zttj": {
          "days": 0,
          "ct": 0
        },
        "hybk": "专用设备"
      },
      {
        "c": "002353",
        "m": 0,
        "n": "杰瑞股份",
        "p": 108000,
        "ztp": 110450,
        "zdp": 7.5590081214904785,
        "amount": 4335236608,
        "ltsz": 74870340120,
        "tshare": 110576430720,
        "hs": 5.777942657470703,
        "fbt": 100330,
        "zbc": 3,
        "zf": 6.981376647949219,
        "zs": 0.5399366617202759,
        "zttj": {
          "days": 0,
          "ct": 0
        },
        "hybk": "专用设备"
      },
      {
        "c": "601975",
        "m": 1,
        "n": "招商南油",
        "p": 4800,
        "ztp": 4960,
        "zdp": 6.430154800415039,
        "amount": 2918003312,
        "ltsz": 22465654454.399998,
        "tshare": 22465653964.8,
        "hs": 12.90714168548584,
        "fbt": 100852,
        "zbc": 4,
        "zf": 12.416851043701172,
        "zs": 0,
        "zttj": {
          "days": 0,
          "ct": 0
        },
        "hybk": "航运港口"
      },
      {
        "c": "603538",
        "m": 1,
        "n": "美诺华",
        "p": 42320,
        "ztp": 43770,
        "zdp": 6.358381271362305,
        "amount": 3905407488,
        "ltsz": 9151004597.76,
        "tshare": 9331045727.36,
        "hs": 43.7974853515625,
        "fbt": 104134,
        "zbc": 1,
        "zf": 15.204826354980469,
        "zs": 0.4033214747905731,
        "zttj": {
          "days": 10,
          "ct": 6
        },
        "hybk": "化学制药"
      },
      {
        "c": "002437",
        "m": 0,
        "n": "誉衡药业",
        "p": 3820,
        "ztp": 3910,
        "zdp": 7.605633735656738,
        "amount": 1875186704,
        "ltsz": 7968709666.82,
        "tshare": 8518096248.96,
        "hs": 23.65118408203125,
        "fbt": 104757,
        "zbc": 1,
        "zf": 10.704225540161133,
        "zs": 0,
        "zttj": {
          "days": 0,
          "ct": 0
        },
        "hybk": "化学制药"
      },
      {
        "c": "000070",
        "m": 0,
        "n": "特发信息",
        "p": 19370,
        "ztp": 20300,
        "zdp": 4.986449718475342,
        "amount": 3875170048,
        "ltsz": 17213709363.24,
        "tshare": 17439678156.16,
        "hs": 22.74998664855957,
        "fbt": 105839,
        "zbc": 1,
        "zf": 13.712737083435059,
        "zs": 0.3107198178768158,
        "zttj": {
          "days": 0,
          "ct": 0
        },
        "hybk": "通信设备"
      },
      {
        "c": "603016",
        "m": 1,
        "n": "新宏泰",
        "p": 51100,
        "ztp": 52270,
        "zdp": 7.533670425415039,
        "amount": 662538368,
        "ltsz": 7570976000,
        "tshare": 7570976000,
        "hs": 8.891180992126465,
        "fbt": 132922,
        "zbc": 1,
        "zf": 12.331649780273438,
        "zs": 0.7094994187355042,
        "zttj": {
          "days": 0,
          "ct": 0
        },
        "hybk": "电网设备"
      },
      {
        "c": "601515",
        "m": 1,
        "n": "衢州东峰",
        "p": 4760,
        "ztp": 5010,
        "zdp": 4.615384578704834,
        "amount": 899624848,
        "ltsz": 9160480393.96,
        "tshare": 9160480398.72,
        "hs": 9.739730834960938,
        "fbt": 142618,
        "zbc": 1,
        "zf": 10.10988998413086,
        "zs": 0.4219409227371216,
        "zttj": {
          "days": 2,
          "ct": 1
        },
        "hybk": "包装印刷"
      },
      {
        "c": "000593",
        "m": 0,
        "n": "德龙汇能",
        "p": 16980,
        "ztp": 17270,
        "zdp": 8.15286636352539,
        "amount": 612274672,
        "ltsz": 6087044209.62,
        "tshare": 6089554515.84,
        "hs": 10.382217407226562,
        "fbt": 145157,
        "zbc": 1,
        "zf": 11.273885726928711,
        "zs": 0,
        "zttj": {
          "days": 0,
          "ct": 0
        },
        "hybk": "燃气Ⅱ"
      }
    ]
  }
}
